<annotation>
	<folder>zhanyejun</folder>
	<filename>1026.jpg</filename>
	<path>C:\Users\A3\Desktop\zhanyejun\1026.jpg</path>
	<source>
		<database>Unknown</database>
	</source>
	<size>
		<width>416</width>
		<height>416</height>
		<depth>1</depth>
	</size>
	<segmented>0</segmented>
	<object>
		<name>sunshang</name>
		<pose>Unspecified</pose>
		<truncated>1</truncated>
		<difficult>0</difficult>
		<bndbox>
			<xmin>330</xmin>
			<ymin>260</ymin>
			<xmax>416</xmax>
			<ymax>312</ymax>
		</bndbox>
	</object>
</annotation>
