<annotation>
	<folder>zhanyejun</folder>
	<filename>1072.jpg</filename>
	<path>C:\Users\A3\Desktop\zhanyejun\1072.jpg</path>
	<source>
		<database>Unknown</database>
	</source>
	<size>
		<width>416</width>
		<height>416</height>
		<depth>1</depth>
	</size>
	<segmented>0</segmented>
	<object>
		<name>sunshang</name>
		<pose>Unspecified</pose>
		<truncated>0</truncated>
		<difficult>0</difficult>
		<bndbox>
			<xmin>20</xmin>
			<ymin>257</ymin>
			<xmax>146</xmax>
			<ymax>311</ymax>
		</bndbox>
	</object>
	<object>
		<name>sunshang</name>
		<pose>Unspecified</pose>
		<truncated>0</truncated>
		<difficult>0</difficult>
		<bndbox>
			<xmin>13</xmin>
			<ymin>346</ymin>
			<xmax>133</xmax>
			<ymax>396</ymax>
		</bndbox>
	</object>
	<object>
		<name>sunshang</name>
		<pose>Unspecified</pose>
		<truncated>1</truncated>
		<difficult>0</difficult>
		<bndbox>
			<xmin>66</xmin>
			<ymin>402</ymin>
			<xmax>240</xmax>
			<ymax>416</ymax>
		</bndbox>
	</object>
</annotation>
