<annotation>
	<folder>luokai</folder>
	<filename>1657.jpg</filename>
	<path>E:\luokai\1657.jpg</path>
	<source>
		<database>Unknown</database>
	</source>
	<size>
		<width>416</width>
		<height>416</height>
		<depth>1</depth>
	</size>
	<segmented>0</segmented>
	<object>
		<name>kongdong</name>
		<pose>Unspecified</pose>
		<truncated>0</truncated>
		<difficult>0</difficult>
		<bndbox>
			<xmin>208</xmin>
			<ymin>61</ymin>
			<xmax>233</xmax>
			<ymax>94</ymax>
		</bndbox>
	</object>
</annotation>
